[
    {
        "iconUrl": "https://raw.githubusercontent.com/DieGon7771/ItaliaInStreaming/master/AltaDefinizione/altadefinizione_icon.png",
        "apiVersion": 1,
        "repositoryUrl": "https://github.com/fciccioend/ENDStreamingITA",
        "fileSize": 21353,
        "status": 1,
        "language": "it",
        "authors": [
            "-END-"
        ],
        "tvTypes": [
            "Movie",
            "TvSeries",
            "Documentary"
        ],
        "version": 5,
        "internalName": "AltaDefinizione",
        "description": "Film e SerieTV da Altadefinizione",
        "url": "https://raw.githubusercontent.com/fciccioend/ENDStreamingITA/main/builds/AltaDefinizione.cs3",
        "name": "AltaDefinizione"
    },
    {
        "iconUrl": "https://www.animeunity.so/apple-touch-icon.png",
        "apiVersion": 1,
        "repositoryUrl": "https://github.com/fciccioend/ENDStreamingITA",
        "fileSize": 35504,
        "status": 1,
        "language": "it",
        "authors": [
            "doGior"
        ],
        "tvTypes": [
            "AnimeMovie",
            "Anime",
            "OVA"
        ],
        "version": 15,
        "internalName": "AnimeUnity",
        "description": "Anime from AnimeUnity",
        "url": "https://raw.githubusercontent.com/fciccioend/ENDStreamingITA/main/builds/AnimeUnity.cs3",
        "name": "AnimeUnity"
    },
    {
        "iconUrl": "https://static.animeworld.ac/assets/images/favicon/android-icon-192x192.png?s",
        "apiVersion": 1,
        "repositoryUrl": "https://github.com/fciccioend/ENDStreamingITA",
        "fileSize": 37465,
        "status": 1,
        "language": "it",
        "authors": [
            "Gian-Fr",
            "doGior"
        ],
        "tvTypes": [
            "AnimeMovie",
            "Anime",
            "OVA"
        ],
        "version": 16,
        "internalName": "AnimeWorld",
        "description": "Anime from AnimeWorld. This plugin is a fork of the AnimeWorld plugin in the ItalianProvider repo",
        "url": "https://raw.githubusercontent.com/fciccioend/ENDStreamingITA/main/builds/AnimeWorld.cs3",
        "name": "AnimeWorld"
    },
    {
        "iconUrl": "https://uno.direttecommunity.online/templates/calciostreaming1/images/icons/apple-touch-icon.png",
        "apiVersion": 1,
        "repositoryUrl": "https://github.com/fciccioend/ENDStreamingITA",
        "fileSize": 12948,
        "status": 1,
        "language": "it",
        "authors": [
            "Gian-Fr",
            "Adippe",
            "doGior"
        ],
        "tvTypes": [
            "Live"
        ],
        "version": 7,
        "internalName": "CalcioStreaming",
        "description": "\u26a0\ufe0fUse AdGuard DNS in the app settings\u26a0\ufe0f Live streams from the CalcioStreaming. Forked from the CalcioStreaming plugin in the ItalianProvider repo",
        "url": "https://raw.githubusercontent.com/fciccioend/ENDStreamingITA/main/builds/CalcioStreaming.cs3",
        "name": "CalcioStreaming"
    },
    {
        "iconUrl": "https://cb01.uno/apple-icon-180x180px.png",
        "apiVersion": 1,
        "repositoryUrl": "https://github.com/fciccioend/ENDStreamingITA",
        "fileSize": 29747,
        "status": 1,
        "language": "it",
        "authors": [
            "doGior"
        ],
        "tvTypes": [
            "Movie",
            "TvSeries",
            "Cartoon"
        ],
        "version": 13,
        "internalName": "CB01",
        "description": "Movies and Shows from CB01",
        "url": "https://raw.githubusercontent.com/fciccioend/ENDStreamingITA/main/builds/CB01.cs3",
        "name": "CB01"
    },
    {
        "iconUrl": "https://raw.githubusercontent.com/doGior/doGiorsHadEnough/refs/heads/master/DaddyLive/live-streaming.png",
        "apiVersion": 1,
        "repositoryUrl": "https://github.com/fciccioend/ENDStreamingITA",
        "fileSize": 31883,
        "status": 0,
        "authors": [
            "doGior"
        ],
        "tvTypes": [
            "Live"
        ],
        "version": 16,
        "internalName": "DaddyLive",
        "description": "Live TV from DaddyLive. You might need a VPN",
        "url": "https://raw.githubusercontent.com/fciccioend/ENDStreamingITA/main/builds/DaddyLive.cs3",
        "name": "DaddyLive"
    },
    {
        "iconUrl": "https://huhu.to/favicon.ico",
        "apiVersion": 1,
        "repositoryUrl": "https://github.com/fciccioend/ENDStreamingITA",
        "fileSize": 23484,
        "status": 1,
        "authors": [
            "doGior"
        ],
        "tvTypes": [
            "Live"
        ],
        "version": 3,
        "internalName": "Huhu",
        "description": "TV channels from huhu.to",
        "url": "https://raw.githubusercontent.com/fciccioend/ENDStreamingITA/main/builds/Huhu.cs3",
        "name": "Huhu"
    },
    {
        "iconUrl": "https://streamingunity.tv/apple-touch-icon.png?v=2",
        "apiVersion": 1,
        "repositoryUrl": "https://github.com/fciccioend/ENDStreamingITA",
        "fileSize": 49721,
        "status": 1,
        "language": "it",
        "authors": [
            "doGior"
        ],
        "tvTypes": [
            "TvSeries",
            "Movie",
            "Documentary",
            "Cartoon"
        ],
        "version": 24,
        "internalName": "StreamingCommunity",
        "description": "TV Shows and Movies from StreamingCommunity (now StreamingUnity)",
        "url": "https://raw.githubusercontent.com/fciccioend/ENDStreamingITA/main/builds/StreamingCommunity.cs3",
        "name": "StreamingCommunity"
    },
    {
        "iconUrl": "https://raw.githubusercontent.com/doGior/doGiorsHadEnough/refs/heads/master/TV/television.png",
        "apiVersion": 1,
        "repositoryUrl": "https://github.com/fciccioend/ENDStreamingITA",
        "fileSize": 27904,
        "status": 1,
        "authors": [
            "Gian-Fr",
            "Adippe",
            "doGior"
        ],
        "tvTypes": [
            "Live"
        ],
        "version": 3,
        "internalName": "TV",
        "description": "Live streams from the Free TV github repository. Forked from the Free-TV plugin in the ItalianProvider repo",
        "url": "https://raw.githubusercontent.com/fciccioend/ENDStreamingITA/main/builds/TV.cs3",
        "name": "TV"
    }
]
